devpi_constrained/__init__.py
devpi_constrained/main.py
devpi_constrained-2.0.1.dist-info/LICENSE
devpi_constrained-2.0.1.dist-info/METADATA
devpi_constrained-2.0.1.dist-info/WHEEL
devpi_constrained-2.0.1.dist-info/entry_points.txt
devpi_constrained-2.0.1.dist-info/top_level.txt
devpi_constrained-2.0.1.dist-info/zip-safe
devpi_constrained-2.0.1.dist-info/RECORD
